nornir_pyfgt/__init__.py
nornir_pyfgt/plugins/__init__.py
nornir_pyfgt/plugins/connections/__init__.py
nornir_pyfgt/plugins/tasks/__init__.py
nornir_pyfgt/plugins/tasks/pyfgt_address.py
nornir_pyfgt/plugins/tasks/pyfgt_address_grp.py
nornir_pyfgt/plugins/tasks/pyfgt_antivirus.py
nornir_pyfgt/plugins/tasks/pyfgt_application.py
nornir_pyfgt/plugins/tasks/pyfgt_delete.py
nornir_pyfgt/plugins/tasks/pyfgt_dhcp_server.py
nornir_pyfgt/plugins/tasks/pyfgt_get_url.py
nornir_pyfgt/plugins/tasks/pyfgt_interface.py
nornir_pyfgt/plugins/tasks/pyfgt_internet_service.py
nornir_pyfgt/plugins/tasks/pyfgt_ip_pool.py
nornir_pyfgt/plugins/tasks/pyfgt_policy_create.py
nornir_pyfgt/plugins/tasks/pyfgt_policy_delete.py
nornir_pyfgt/plugins/tasks/pyfgt_policy_get.py
nornir_pyfgt/plugins/tasks/pyfgt_post_url.py
nornir_pyfgt/plugins/tasks/pyfgt_put_url.py
nornir_pyfgt/plugins/tasks/pyfgt_send_command.py
nornir_pyfgt/plugins/tasks/pyfgt_service.py
nornir_pyfgt/plugins/tasks/pyfgt_service_category.py
nornir_pyfgt/plugins/tasks/pyfgt_service_group.py
nornir_pyfgt/plugins/tasks/pyfgt_virtual_ip.py
nornir_pyfgt/plugins/tasks/pyfgt_zone.py
nornir_pyfgt-1.0.3.dist-info/entry_points.txt
nornir_pyfgt-1.0.3.dist-info/LICENSE
nornir_pyfgt-1.0.3.dist-info/METADATA
nornir_pyfgt-1.0.3.dist-info/WHEEL
nornir_pyfgt-1.0.3.dist-info/RECORD
