Metadata-Version: 2.1
Name: nornir-pyfgt
Version: 1.0.3
Summary: Fortigate-api plugin for Nornir
Home-page: https://github.com/gt732/nornir_pyfgt
License: MIT
Author: GT
Author-email: geuryt@yahoo.com
Requires-Python: >=3.8,<4.0
Classifier: License :: OSI Approved :: MIT License
Classifier: Programming Language :: Python :: 3
Classifier: Programming Language :: Python :: 3.8
Classifier: Programming Language :: Python :: 3.9
Classifier: Programming Language :: Python :: 3.10
Classifier: Programming Language :: Python :: 3.11
Requires-Dist: fortigate-api (>=1.0.1,<2.0.0)
Project-URL: Repository, https://github.com/gt732/nornir_pyfgt
